mtaa/__init__.py
mtaa/tanzania_json.py
mtaa-1.5.dist-info/LICENSE
mtaa-1.5.dist-info/METADATA
mtaa-1.5.dist-info/WHEEL
mtaa-1.5.dist-info/top_level.txt
mtaa-1.5.dist-info/RECORD
